awsunusedresources/__init__.py
awsunusedresources/aws_resources.py
awsunusedresources-0.1.6.dist-info/LICENSE.txt
awsunusedresources-0.1.6.dist-info/METADATA
awsunusedresources-0.1.6.dist-info/WHEEL
awsunusedresources-0.1.6.dist-info/top_level.txt
awsunusedresources-0.1.6.dist-info/RECORD
