Metadata-Version: 2.1
Name: awsunusedresources
Version: 0.1.6
Summary: A package for identifying unused resources in aws
Home-page: https://github.com/karthickcse05/aws_unused_res
Author: Karthickcse05
Author-email: Karthickcse05@gmail.com
License: UNKNOWN
Platform: UNKNOWN
Classifier: Programming Language :: Python :: 3
Classifier: License :: OSI Approved :: MIT License
Classifier: Operating System :: OS Independent
Requires-Python: >=3.7.0
Requires-Dist: pandas (==1.1.2)
